daikinPyZone/__init__.py
daikinPyZone/daikinCalculate.py
daikinPyZone/daikinClasses.py
daikinPyZone/daikinConstants.py
daikinPyZone/daikinProcess.py
daikinPyZone-1.0.dist-info/LICENSE
daikinPyZone-1.0.dist-info/METADATA
daikinPyZone-1.0.dist-info/WHEEL
daikinPyZone-1.0.dist-info/top_level.txt
daikinPyZone-1.0.dist-info/RECORD
