Metadata-Version: 2.1
Name: daikinPyZone
Version: 1.0
Summary: Daikin Skyzone API for Python
Home-page: https://github.com/BenNeumeister/daikinPyZone
Author: Ben Neumeister
Author-email: benneumeister@gmail.com
Classifier: Programming Language :: Python :: 3
Classifier: License :: OSI Approved :: GNU General Public License v3 (GPLv3)
Classifier: Operating System :: OS Independent
License-File: LICENSE
